<?xml version="1.0"?>
<types-tool>
 <type id="Book"/>
 <type id="CPS Proxy BTree Folder"
       filename="types/CPS_Proxy_BTree_Folder.xml"/>
 <type id="CPS Proxy BTree Folderish Document"
       filename="types/CPS_Proxy_BTree_Folderish_Document.xml"/>
 <type id="CPS Proxy Document"
       filename="types/CPS_Proxy_Document.xml"/>
 <type id="CPS Proxy Folder"
       filename="types/CPS_Proxy_Folder.xml"/>
 <type id="CPS Proxy Folderish Document"
       filename="types/CPS_Proxy_Folderish_Document.xml"/>
 <type id="CPSForum"/>
 <type id="Calendar"/>
 <type id="Chapter"/>
 <type id="Chat"/>
 <type id="ChatItem"/>
 <type id="Collector Document"
       filename="types/Collector_Document.xml"/>
 <type id="Discussion Item"
       filename="types/Discussion_Item.xml"/>
 <type id="Document"/>
 <type id="Event"/>
 <type id="EventDoc"/>
 <type id="FAQ"/>
 <type id="FAQitem"/>
 <type id="File"/>
 <type id="Flash Animation"
       filename="types/Flash_Animation.xml"/>
 <type id="Flexible"/>
 <type id="Folder"/>
 <type id="ForumPost"/>
 <type id="Glossary"/>
 <type id="GlossaryItem"/>
 <type id="Image"/>
 <type id="ImageGallery"/>
 <type id="Link"/>
 <type id="News Item" filename="types/News_Item.xml"/>
 <type id="NewsLetter"/>
 <type id="OOoDocbookDocument"/>
 <type id="Page"/>
 <type id="Press Release" filename="types/Press_Release.xml"/>
 <type id="Quiz Document" filename="types/Quiz_Document.xml"/>
 <type id="RSS Box" filename="types/RSS_Box.xml"/>
 <type id="Section"/>
 <type id="Wiki"/>
 <type id="Wiki Page" filename="types/Wiki_Page.xml"/>
 <type id="Workspace"/>
 <type id="ZippedHtml"/>
</types-tool>
