<?xml version="1.0"?>
<object name="subject_voc" meta_type="CPS Vocabulary">
 <property name="title"></property>
 <property name="title_msgid"></property>
 <property name="description"></property>
 <property name="acl_write_roles">Manager</property>
 <item key="Arts" msgid="label_subject_Arts">Arts</item>
 <item key="Business" msgid="label_subject_Business">Business</item>
 <item key="Computers" msgid="label_subject_Computers">Computers</item>
 <item key="Games" msgid="label_subject_Games">Games</item>
 <item key="Health" msgid="label_subject_Health">Health</item>
 <item key="Home" msgid="label_subject_Home">Home</item>
 <item key="Kids and Teens"
    msgid="label_subject_Kids and Teens">Kids and Teens</item>
 <item key="News" msgid="label_subject_News">News</item>
 <item key="Recreation" msgid="label_subject_Recreation">Recreation</item>
 <item key="Reference" msgid="label_subject_Reference">Reference</item>
 <item key="Regional" msgid="label_subject_Regional">Regional</item>
 <item key="Science" msgid="label_subject_Science">Science</item>
 <item key="Shopping" msgid="label_subject_Shopping">Shopping</item>
 <item key="Society" msgid="label_subject_Society">Society</item>
 <item key="Sports" msgid="label_subject_Sports">Sports</item>
</object>
